Metadata-Version: 1.0
Name: sample-manero-pypi-project
Version: 0.0.1
Summary: Sample desc
Home-page: http://packages.python.org/sample_manero_pypi_project
Author: Manero
Author-email: my.bin@live.com
License: BSD
Keywords: Sample
Platform: UNKNOWN
